smbus3/__init__.py
smbus3/py.typed
smbus3/smbus3.py
smbus3/smbus3.pyi
smbus3-0.5.5.dist-info/LICENSE
smbus3-0.5.5.dist-info/METADATA
smbus3-0.5.5.dist-info/WHEEL
smbus3-0.5.5.dist-info/top_level.txt
smbus3-0.5.5.dist-info/RECORD
