Metadata-Version: 2.1
Name: smbus3
Version: 0.5.5
Summary: smbus3 is a drop-in replacement for smbus2, smbus-cffi, smbus-python written in pure Python, intended for use with Python 3.8+ on Unix-like systems
Home-page: https://github.com/eindiran/smbus3
Author: Elliott Indiran
Author-email: elliott.indiran@protonmail.com
License: MIT
Keywords: smbus,smbus2,smbus3,python,i2c,raspberrypi,linux
Platform: linux
Platform: unix
Platform: posix
Platform: macos
Platform: bsd
Classifier: Development Status :: 5 - Production/Stable
Classifier: Topic :: Software Development :: Libraries :: Python Modules
Classifier: Topic :: System :: Hardware
Classifier: Topic :: Utilities
Classifier: License :: OSI Approved :: MIT License
Classifier: Programming Language :: Python :: Implementation :: CPython
Classifier: Programming Language :: Python :: 3
Classifier: Programming Language :: Python :: 3 :: Only
Classifier: Programming Language :: Python :: 3.8
Classifier: Programming Language :: Python :: 3.9
Classifier: Programming Language :: Python :: 3.10
Classifier: Programming Language :: Python :: 3.11
Classifier: Programming Language :: Python :: 3.12
Classifier: Operating System :: MacOS
Classifier: Operating System :: POSIX :: BSD
Classifier: Operating System :: POSIX :: Linux
Classifier: Typing :: Typed
Classifier: Natural Language :: English
Requires-Python: >=3.8
License-File: LICENSE
Provides-Extra: docs
Requires-Dist: sphinx>=7.0.0; extra == "docs"
